aiobafi6/__init__.py
aiobafi6/cmd/__init__.py
aiobafi6/cmd/main.py
aiobafi6/const.py
aiobafi6/device.py
aiobafi6/device_test.py
aiobafi6/discovery.py
aiobafi6/exceptions.py
aiobafi6/proto/aiobafi6_pb2.py
aiobafi6/proto/aiobafi6_pb2.pyi
aiobafi6/protoprop.py
aiobafi6/protoprop_test.py
aiobafi6/wireutils.py
aiobafi6/wireutils_test.py
aiobafi6-0.10.2.dist-info/METADATA
aiobafi6-0.10.2.dist-info/WHEEL
aiobafi6-0.10.2.dist-info/entry_points.txt
aiobafi6-0.10.2.dist-info/licenses/LICENSE
aiobafi6-0.10.2.dist-info/RECORD
