Metadata-Version: 2.4
Name: aiobafi6
Version: 0.10.2
Summary: Big Ass Fans i6/Haiku protocol asynchronous Python library
License: Apache-2.0
License-File: LICENSE
Keywords: BigAssFans,i6,Haiku,SenseME
Author: Jean-Francois Roy
Author-email: jf@devklog.net
Requires-Python: >=3.11.0
Classifier: Framework :: AsyncIO
Classifier: Intended Audience :: Developers
Classifier: License :: OSI Approved :: Apache Software License
Classifier: Programming Language :: Python :: 3
Classifier: Programming Language :: Python :: 3.11
Classifier: Programming Language :: Python :: 3.12
Classifier: Programming Language :: Python :: 3.13
Classifier: Programming Language :: Python :: 3.14
Classifier: Topic :: Home Automation
Requires-Dist: protobuf (>=3.20)
Requires-Dist: zeroconf (>=0.38)
Project-URL: Homepage, https://github.com/jfroy/aiobafi6
Project-URL: Repository, https://github.com/jfroy/aiobafi6
